__init__.py
taranis_pb2.py
taranis_pb2_grpc.py
taranis_cli.egg-info/PKG-INFO
taranis_cli.egg-info/SOURCES.txt
taranis_cli.egg-info/dependency_links.txt
taranis_cli.egg-info/requires.txt
taranis_cli.egg-info/top_level.txt
taranis_cli-0.3.3.dist-info/METADATA
taranis_cli-0.3.3.dist-info/WHEEL
taranis_cli-0.3.3.dist-info/top_level.txt
taranis_cli-0.3.3.dist-info/RECORD
