Metadata-Version: 2.1
Name: taranis-cli
Version: 0.3.3
Summary: Taranis client
Home-page: https://github.com/pletessier/taranis
Author: Pierre Letessier
Author-email: UNKNOWN
License: UNKNOWN
Keywords: lib,taranis,client
Platform: UNKNOWN
Requires-Dist: grpcio (==1.21.1)
Requires-Dist: grpcio-tools (==1.21.1)
